setup.py
ana_survey/__init__.py
ana_survey/ana_survey.py
ana_survey.egg-info/PKG-INFO
ana_survey.egg-info/SOURCES.txt
ana_survey.egg-info/dependency_links.txt
ana_survey.egg-info/not-zip-safe
ana_survey.egg-info/top_level.txt