Metadata-Version: 1.0
Name: ana-survey
Version: 1.0
Summary: Package to analysis the survey data for BELLEII B field measurement campaign
Home-page: UNKNOWN
Author: guoaq
Author-email: guoaq@foxmail.com
License: DESY
Platform: UNKNOWN
